hubrdvmairie/__init__.py
hubrdvmairie/controllers/__init__.py
hubrdvmairie/controllers/controller.py
hubrdvmairie/controllers/dependencies/auth_token.py
hubrdvmairie/controllers/routes/__init__.py
hubrdvmairie/controllers/routes/data.py
hubrdvmairie/controllers/routes/external.py
hubrdvmairie/controllers/routes/internal.py
hubrdvmairie/controllers/routes/time_slots.py
hubrdvmairie/controllers/routes/websocket.py
hubrdvmairie/core/__init__.py
hubrdvmairie/core/config.py
hubrdvmairie/core/custom_validation_error.py
hubrdvmairie/crud/__init__.py
hubrdvmairie/crud/base.py
hubrdvmairie/crud/crud_certified_municipality.py
hubrdvmairie/crud/crud_editor.py
hubrdvmairie/crud/crud_editor_panorama.py
hubrdvmairie/crud/crud_meeting_point.py
hubrdvmairie/crud/crud_token_ants_to_editor.py
hubrdvmairie/crud/crud_token_editor_to_ants.py
hubrdvmairie/db/__init__.py
hubrdvmairie/db/postgresdb.py
hubrdvmairie/db/postgresdb_utils.py
hubrdvmairie/db/schemas.py
hubrdvmairie/db/utils.py
hubrdvmairie/logging/__init__.py
hubrdvmairie/logging/app_logger.py
hubrdvmairie/logging/app_logger_formatter.py
hubrdvmairie/models/__init__.py
hubrdvmairie/models/announcement.py
hubrdvmairie/models/application.py
hubrdvmairie/models/available_time_slot.py
hubrdvmairie/models/certified_municipality.py
hubrdvmairie/models/editor.py
hubrdvmairie/models/editor_model.py
hubrdvmairie/models/editor_panorama.py
hubrdvmairie/models/meeting_point.py
hubrdvmairie/models/municipality.py
hubrdvmairie/models/token_ants_to_editor.py
hubrdvmairie/models/token_editor_to_ants.py
hubrdvmairie/schemas/__init__.py
hubrdvmairie/schemas/certified_municipality.py
hubrdvmairie/schemas/editor.py
hubrdvmairie/schemas/editor_panorama.py
hubrdvmairie/schemas/meeting_point.py
hubrdvmairie/schemas/token_ants_to_editor.py
hubrdvmairie/schemas/token_editor_to_ants.py
hubrdvmairie/services/__init__.py
hubrdvmairie/services/certified_municipality_service.py
hubrdvmairie/services/data_validator.py
hubrdvmairie-3.4.1.dist-info/LICENSE
hubrdvmairie-3.4.1.dist-info/METADATA
hubrdvmairie-3.4.1.dist-info/WHEEL
hubrdvmairie-3.4.1.dist-info/top_level.txt
hubrdvmairie-3.4.1.dist-info/RECORD
